{
  "indexes": [
    {
      "collectionGroup": "course_announcements",
      "queryScope": "COLLECTION",
      "fields": [
        { "fieldPath": "courseCode", "order": "ASCENDING" },
        { "fieldPath": "eventDate", "order": "DESCENDING" }
      ]
    },
    {
      "collectionGroup": "acad_drives_files",
      "queryScope": "COLLECTION",
      "fields": [
        { "fieldPath": "course_codes", "arrayConfig": "CONTAINS" },
        { "fieldPath": "uploadedAt", "order": "DESCENDING" }
      ]
    },
    {
      "collectionGroup": "acad_drives_index",
      "queryScope": "COLLECTION",
      "fields": [
        { "fieldPath": "fileCount", "order": "ASCENDING" },
        { "fieldPath": "code", "order": "ASCENDING" }
      ]
    },
    {
      "collectionGroup": "acad_drives_index",
      "queryScope": "COLLECTION",
      "fields": [
        { "fieldPath": "fileCount", "order": "DESCENDING" },
        { "fieldPath": "code", "order": "DESCENDING" }
      ]
    }
  ],
  "fieldOverrides": []
}
